[
    {
        "lat": 17.90785,
        "long": -62.8364
    },
    {
        "lat": 17.91042,
        "long": -62.83606
    },
    {
        "lat": 17.91335,
        "long": -62.8368
    },
    {
        "lat": 17.91456,
        "long": -62.83733
    },
    {
        "lat": 17.91614,
        "long": -62.83817
    },
    {
        "lat": 17.91779,
        "long": -62.83919
    },
    {
        "lat": 17.91911,
        "long": -62.84026
    },
    {
        "lat": 17.92044,
        "long": -62.8416
    },
    {
        "lat": 17.92159,
        "long": -62.84315
    },
    {
        "lat": 17.92351,
        "long": -62.84676
    },
    {
        "lat": 17.92433,
        "long": -62.84859
    },
    {
        "lat": 17.92755,
        "long": -62.85646
    },
    {
        "lat": 17.92836,
        "long": -62.85861
    },
    {
        "lat": 17.92932,
        "long": -62.86107
    },
    {
        "lat": 17.93178,
        "long": -62.8673
    },
    {
        "lat": 17.93344,
        "long": -62.87162
    },
    {
        "lat": 17.93509,
        "long": -62.87603
    },
    {
        "lat": 17.93665,
        "long": -62.8803
    },
    {
        "lat": 17.93825,
        "long": -62.88491
    },
    {
        "lat": 17.94081,
        "long": -62.89167
    },
    {
        "lat": 17.94292,
        "long": -62.89851
    },
    {
        "lat": 17.94347,
        "long": -62.90075
    },
    {
        "lat": 17.94406,
        "long": -62.90347
    },
    {
        "lat": 17.94447,
        "long": -62.90559
    },
    {
        "lat": 17.94525,
        "long": -62.91032
    },
    {
        "lat": 17.94553,
        "long": -62.91244
    },
    {
        "lat": 17.94589,
        "long": -62.91735
    },
    {
        "lat": 17.94598,
        "long": -62.91973
    },
    {
        "lat": 17.94608,
        "long": -62.92212
    },
    {
        "lat": 17.94612,
        "long": -62.92439
    },
    {
        "lat": 17.94617,
        "long": -62.92665
    },
    {
        "lat": 17.94621,
        "long": -62.9342
    },
    {
        "lat": 17.94607,
        "long": -62.93646
    },
    {
        "lat": 17.94589,
        "long": -62.93822
    },
    {
        "lat": 17.94553,
        "long": -62.94115
    },
    {
        "lat": 17.94347,
        "long": -62.95243
    },
    {
        "lat": 17.94253,
        "long": -62.95593
    },
    {
        "lat": 17.94168,
        "long": -62.95807
    },
    {
        "lat": 17.93946,
        "long": -62.96196
    },
    {
        "lat": 17.93779,
        "long": -62.96412
    },
    {
        "lat": 17.9366,
        "long": -62.96549
    },
    {
        "lat": 17.93541,
        "long": -62.96693
    },
    {
        "lat": 17.93376,
        "long": -62.96886
    },
    {
        "lat": 17.93033,
        "long": -62.97296
    },
    {
        "lat": 17.92754,
        "long": -62.97633
    },
    {
        "lat": 17.92424,
        "long": -62.98035
    },
    {
        "lat": 17.92135,
        "long": -62.98403
    },
    {
        "lat": 17.91912,
        "long": -62.98702
    },
    {
        "lat": 17.94756,
        "long": -63.05755
    },
    {
        "lat": 17.95068,
        "long": -63.06084
    },
    {
        "lat": 17.95385,
        "long": -63.06417
    },
    {
        "lat": 17.95715,
        "long": -63.0678
    },
    {
        "lat": 17.96031,
        "long": -63.07126
    },
    {
        "lat": 17.96363,
        "long": -63.07486
    },
    {
        "lat": 17.96686,
        "long": -63.07839
    },
    {
        "lat": 17.97038,
        "long": -63.08202
    },
    {
        "lat": 17.97533,
        "long": -63.08711
    },
    {
        "lat": 17.97862,
        "long": -63.09053
    },
    {
        "lat": 17.98592,
        "long": -63.09797
    },
    {
        "lat": 17.98858,
        "long": -63.10145
    },
    {
        "lat": 17.98952,
        "long": -63.10306
    },
    {
        "lat": 17.98974,
        "long": -63.10341
    },
    {
        "lat": 17.99067,
        "long": -63.10537
    },
    {
        "lat": 17.9916,
        "long": -63.10763
    },
    {
        "lat": 17.99263,
        "long": -63.11052
    },
    {
        "lat": 17.99345,
        "long": -63.11303
    },
    {
        "lat": 17.9941,
        "long": -63.1153
    },
    {
        "lat": 17.99551,
        "long": -63.12002
    },
    {
        "lat": 17.99598,
        "long": -63.12165
    },
    {
        "lat": 17.99625,
        "long": -63.12248
    },
    {
        "lat": 17.99744,
        "long": -63.12609
    },
    {
        "lat": 17.9977,
        "long": -63.12695
    },
    {
        "lat": 17.99821,
        "long": -63.12841
    },
    {
        "lat": 17.99984,
        "long": -63.13313
    },
    {
        "lat": 18.00156,
        "long": -63.13771
    },
    {
        "lat": 18.00325,
        "long": -63.14223
    },
    {
        "lat": 18.00412,
        "long": -63.14456
    },
    {
        "lat": 18.00594,
        "long": -63.14897
    },
    {
        "lat": 18.00799,
        "long": -63.15348
    },
    {
        "lat": 18.00924,
        "long": -63.15564
    },
    {
        "lat": 18.01013,
        "long": -63.15692
    },
    {
        "lat": 18.01163,
        "long": -63.15876
    },
    {
        "lat": 18.01344,
        "long": -63.16065
    },
    {
        "lat": 18.01544,
        "long": -63.16241
    },
    {
        "lat": 18.01683,
        "long": -63.16349
    },
    {
        "lat": 18.01712,
        "long": -63.16368
    },
    {
        "lat": 18.01865,
        "long": -63.16467
    },
    {
        "lat": 18.01902,
        "long": -63.16486
    },
    {
        "lat": 18.02275,
        "long": -63.16647
    },
    {
        "lat": 18.02512,
        "long": -63.16697
    },
    {
        "lat": 18.02689,
        "long": -63.16702
    },
    {
        "lat": 18.02759,
        "long": -63.16697
    },
    {
        "lat": 18.02917,
        "long": -63.16668
    },
    {
        "lat": 18.03099,
        "long": -63.16599
    },
    {
        "lat": 18.03122,
        "long": -63.16589
    },
    {
        "lat": 18.03268,
        "long": -63.16498
    },
    {
        "lat": 18.0341,
        "long": -63.16363
    },
    {
        "lat": 18.03434,
        "long": -63.16334
    },
    {
        "lat": 18.03539,
        "long": -63.16156
    },
    {
        "lat": 18.03597,
        "long": -63.16001
    },
    {
        "lat": 18.03634,
        "long": -63.15594
    },
    {
        "lat": 18.03615,
        "long": -63.15368
    },
    {
        "lat": 18.03606,
        "long": -63.15304
    },
    {
        "lat": 18.03587,
        "long": -63.15182
    },
    {
        "lat": 18.03573,
        "long": -63.15074
    },
    {
        "lat": 18.03555,
        "long": -63.14883
    },
    {
        "lat": 18.0355,
        "long": -63.14765
    },
    {
        "lat": 18.03545,
        "long": -63.14642
    },
    {
        "lat": 18.03561,
        "long": -63.14272
    },
    {
        "lat": 18.03566,
        "long": -63.14228
    },
    {
        "lat": 18.03583,
        "long": -63.14103
    },
    {
        "lat": 18.03601,
        "long": -63.13995
    },
    {
        "lat": 18.03629,
        "long": -63.13877
    },
    {
        "lat": 18.03653,
        "long": -63.13764
    },
    {
        "lat": 18.03666,
        "long": -63.1371
    },
    {
        "lat": 18.03694,
        "long": -63.13593
    },
    {
        "lat": 18.03708,
        "long": -63.1352
    },
    {
        "lat": 18.03726,
        "long": -63.13428
    },
    {
        "lat": 18.0374,
        "long": -63.13356
    },
    {
        "lat": 18.03764,
        "long": -63.13244
    },
    {
        "lat": 18.03795,
        "long": -63.13024
    },
    {
        "lat": 18.03827,
        "long": -63.12816
    },
    {
        "lat": 18.03839,
        "long": -63.12739
    },
    {
        "lat": 18.0385,
        "long": -63.12667
    },
    {
        "lat": 18.03853,
        "long": -63.12626
    },
    {
        "lat": 18.03854,
        "long": -63.12585
    },
    {
        "lat": 18.03859,
        "long": -63.12552
    },
    {
        "lat": 18.03863,
        "long": -63.12508
    },
    {
        "lat": 18.03871,
        "long": -63.12465
    },
    {
        "lat": 18.039,
        "long": -63.12248
    },
    {
        "lat": 18.03932,
        "long": -63.12028
    },
    {
        "lat": 18.0396,
        "long": -63.11847
    },
    {
        "lat": 18.03988,
        "long": -63.11631
    },
    {
        "lat": 18.04011,
        "long": -63.11464
    },
    {
        "lat": 18.04026,
        "long": -63.11357
    },
    {
        "lat": 18.04033,
        "long": -63.11328
    },
    {
        "lat": 18.04046,
        "long": -63.11307
    },
    {
        "lat": 18.04073,
        "long": -63.11289
    },
    {
        "lat": 18.04098,
        "long": -63.1129
    }
]